MANIFEST.in
README.rst
requirements.txt
requirements_docs.txt
setup.cfg
setup.py
docs/Examples.rst
docs/Makefile
docs/conf.py
docs/index.rst
docs/make.bat
docs/_static/silab.ico
docs/_static/example_fei4/AlignmentCorrFit.png
docs/_static/example_fei4/AlignmentCorrSlice.png
docs/_static/example_fei4/CorrelationColumn.png
docs/_static/example_fei4/CorrelationRow.png
docs/_static/example_fei4/Efficiency.png
docs/_static/example_fei4/EventMonitor.png
docs/_static/example_fei4/Track_chi2.png
testbeam_analysis/__init__.py
testbeam_analysis/dut_alignment.py
testbeam_analysis/hit_analysis.py
testbeam_analysis/result_analysis.py
testbeam_analysis/track_analysis.py
testbeam_analysis.egg-info/PKG-INFO
testbeam_analysis.egg-info/SOURCES.txt
testbeam_analysis.egg-info/dependency_links.txt
testbeam_analysis.egg-info/requires.txt
testbeam_analysis.egg-info/top_level.txt
testbeam_analysis/converter/__init__.py
testbeam_analysis/converter/eudaq_converter.py
testbeam_analysis/converter/pybar_fei4_converter.py
testbeam_analysis/cpp/AnalysisFunctions.h
testbeam_analysis/cpp/__init__.py
testbeam_analysis/cpp/analysis_functions.cpp
testbeam_analysis/cpp/analysis_functions.pyx
testbeam_analysis/cpp/data_struct.pxd
testbeam_analysis/cpp/data_struct.py
testbeam_analysis/cpp/defines.h
testbeam_analysis/cpp/external/changelog.txt
testbeam_analysis/cpp/external/inttypes.h
testbeam_analysis/cpp/external/stdint.h
testbeam_analysis/examples/__init__.py
testbeam_analysis/examples/eutelescope.py
testbeam_analysis/examples/fei4_telescope.py
testbeam_analysis/examples/simulated_data.py
testbeam_analysis/examples/telescope_time_reference.py
testbeam_analysis/examples/data/HOWTO.txt
testbeam_analysis/testing/test_alignment.py
testbeam_analysis/testing/test_analysis_utils.py
testbeam_analysis/testing/test_correlation_fixing.py
testbeam_analysis/testing/test_examples.py
testbeam_analysis/testing/test_geometry_utils.py
testbeam_analysis/testing/test_hit_analysis.py
testbeam_analysis/testing/test_result_analysis.py
testbeam_analysis/testing/test_simulation.py
testbeam_analysis/testing/test_track_analysis.py
testbeam_analysis/testing/fixtures/analysis_utils/hist_data.h5
