Metadata-Version: 1.0
Name: testbeam-analysis
Version: 0.0.1
Summary: A light weight test beam analysis in Python and C++.
Home-page: https://github.com/SiLab-Bonn/testbeam_analysis
Author: David-Leon Pohl, Christian Bespin, Jens Janssen, Luigi Vigani
Author-email: pohl@physik.uni-bonn.de
License: BSD 3-Clause ("BSD New" or "BSD Simplified") License
Keywords: testbeam,particle,reconstruction,pixel,detector
Platform: any
